tools_mp/__init__.py
tools_mp/processor.py
tools_mp-0.3.0.dist-info/LICENSE
tools_mp-0.3.0.dist-info/METADATA
tools_mp-0.3.0.dist-info/WHEEL
tools_mp-0.3.0.dist-info/top_level.txt
tools_mp-0.3.0.dist-info/zip-safe
tools_mp-0.3.0.dist-info/RECORD
