Metadata-Version: 2.2
Name: tools-mp
Version: 0.3.0
Summary: Convenient multiprocessing function for Python
Home-page: https://github.com/paul-krug/tools-mp
Author: Paul Krug
Author-email: paul_konstantin.krug@tu-dresden.de
License: MIT
Keywords: multiprocessing,Python
Classifier: Development Status :: 3 - Alpha
Classifier: Intended Audience :: Science/Research
Classifier: Intended Audience :: Developers
Classifier: License :: OSI Approved :: MIT License
Classifier: Programming Language :: Python
Classifier: Programming Language :: Python :: 3
Classifier: Programming Language :: Python :: 3.8
Classifier: Programming Language :: Python :: 3.9
Classifier: Programming Language :: Python :: 3.10
Classifier: Topic :: Software Development
Classifier: Topic :: Scientific/Engineering
Classifier: Typing :: Typed
Classifier: Operating System :: Microsoft :: Windows
Classifier: Operating System :: POSIX
Classifier: Operating System :: Unix
License-File: LICENSE
Requires-Dist: tqdm>=4.62.1
Dynamic: author
Dynamic: author-email
Dynamic: classifier
Dynamic: home-page
Dynamic: keywords
Dynamic: license
Dynamic: requires-dist
Dynamic: summary
